flask_auth_middleware/__init__.py
flask_auth_middleware/auth_decorator.py
flask_auth_middleware/auth_middleware.py
flask_auth_middleware-0.3.0.dist-info/LICENSE
flask_auth_middleware-0.3.0.dist-info/METADATA
flask_auth_middleware-0.3.0.dist-info/WHEEL
flask_auth_middleware-0.3.0.dist-info/top_level.txt
flask_auth_middleware-0.3.0.dist-info/RECORD
